spectraxgk/__init__.py
spectraxgk/backends.py
spectraxgk/cli.py
spectraxgk/constants.py
spectraxgk/dg.py
spectraxgk/diagnostics.py
spectraxgk/fourier.py
spectraxgk/hermite_ops.py
spectraxgk/io_config.py
spectraxgk/plots.py
spectraxgk/poisson.py
spectraxgk/util.py
spectraxgk-0.0.1.dist-info/licenses/LICENSE
spectraxgk-0.0.1.dist-info/METADATA
spectraxgk-0.0.1.dist-info/WHEEL
spectraxgk-0.0.1.dist-info/entry_points.txt
spectraxgk-0.0.1.dist-info/top_level.txt
spectraxgk-0.0.1.dist-info/RECORD
