Metadata-Version: 2.4
Name: spectraxgk
Version: 0.0.1
Summary: Fourier–Hermite and DG solvers for multispecies Gyrokinetic equation with JAX.
Author-email: UWPlasma <rogerio.jorge@wisc.edu>
License: MIT
Keywords: plasma,vlasov,poisson,fourier,hermite,discontinuous-galerkin,jax
Classifier: Programming Language :: Python :: 3
Classifier: License :: OSI Approved :: MIT License
Classifier: Operating System :: OS Independent
Classifier: Topic :: Scientific/Engineering :: Physics
Requires-Python: >=3.10
License-File: LICENSE
Requires-Dist: numpy
Requires-Dist: matplotlib
Requires-Dist: jax
Requires-Dist: diffrax
Provides-Extra: dev
Requires-Dist: pytest; extra == "dev"
Requires-Dist: pytest-cov; extra == "dev"
Requires-Dist: ruff; extra == "dev"
Requires-Dist: mypy; extra == "dev"
Requires-Dist: build; extra == "dev"
Provides-Extra: docs
Requires-Dist: mkdocs-material; extra == "docs"
Requires-Dist: mkdocstrings[python]; extra == "docs"
Requires-Dist: pymdown-extensions; extra == "docs"
Dynamic: license-file
